dsl_spa/__init__.py
dsl_spa/pipeline/__init__.py
dsl_spa/pipeline/connector.py
dsl_spa/pipeline/pipeline.py
dsl_spa/pipeline/pipeline_functions.py
dsl_spa/pipeline/semantic_cache_pipeline.py
dsl_spa/utils/__init__.py
dsl_spa/utils/schema.py
dsl_spa-0.4.1.dist-info/licenses/LICENSE
dsl_spa-0.4.1.dist-info/METADATA
dsl_spa-0.4.1.dist-info/WHEEL
dsl_spa-0.4.1.dist-info/top_level.txt
dsl_spa-0.4.1.dist-info/RECORD
