Metadata-Version: 2.4
Name: dsl-spa
Version: 0.4.1
Summary: A tool for building Structured Agentic Pipelines
Author-email: superwise-brian <brian.mcclannahan@superwise.ai>
License-Expression: MIT
Project-URL: Homepage, https://github.com/superwise-ai/dsl-spa
Project-URL: Issues, https://github.com/superwise-ai/dsl-spa/issues
Classifier: Programming Language :: Python :: 3
Classifier: Operating System :: OS Independent
Requires-Python: >=3.9
License-File: LICENSE
Requires-Dist: setuptools>=77.0.3
Requires-Dist: pandas>=2.0.0
Requires-Dist: altair>=5.3.0
Requires-Dist: SQLAlchemy>=2.0.0
Requires-Dist: langchain-openai>=0.3.3
Requires-Dist: sentence-transformers>=3.4.1
Dynamic: license-file
